{
  "id": "ab7f7e2c-3660-4f40-990f-dfed7309a7ad",
  "created_at": "2025-05-09T01:34:24.968494Z",
  "updated_at": "2025-05-27T01:34:24.968496Z",
  "title": "Managed dedicated concept",
  "description": "Degree minute strategy space role fear how director. Operation school argue around with others white. Up live minute center southern maintain. I property difficult account control.",
  "status": "active",
  "difficulty": "medium",
  "theme": "mystery",
  "npc_id": "f6856d94-b11e-4a94-91e3-d13090ebccd0",
  "player_id": "19fa86e0-8fc3-4f44-81f9-6e5bb0eac29a",
  "level": 2,
  "rewards": {
    "gold": 913,
    "experience": 1635,
    "reputation": {},
    "items": [
      {
        "item_id": "780565ad-6f74-461d-826c-bce94b2e400c",
        "quantity": 1
      }
    ],
    "special": {}
  },
  "steps": [
    {
      "id": 1,
      "title": "Investigate the scene",
      "description": "Safe rest glass seat after common whom.",
      "completed": false,
      "required": true,
      "order": 1,
      "metadata": {
        "target_id": "17d27b83-d909-4ec4-bdf1-708f550c7c8a"
      }
    },
    {
      "id": 2,
      "title": "Deliver evidence",
      "description": "Subject morning trial a life although administration.",
      "completed": true,
      "required": true,
      "order": 2,
      "metadata": {
        "target_id": "572b5c0a-099a-454c-a902-433bebb5aeec"
      }
    },
    {
      "id": 3,
      "title": "Report findings",
      "description": "Can voice where two simply.",
      "completed": true,
      "required": true,
      "order": 3,
      "metadata": {
        "target_id": "3074b561-88e9-4ad7-a70d-a977b24054f3"
      }
    }
  ],
  "properties": {
    "legacy_quest_type": "SIDE",
    "legacy_target_character_id": "19fa86e0-8fc3-4f44-81f9-6e5bb0eac29a"
  }
}