{
  "character_id": "<MagicMock name='mock.query().filter().first().uuid' id='4402429520'>",
  "goals": [
    {
      "goal_id": "4e6413d0-2e76-487b-a249-69b6ec004048",
      "character_id": "<MagicMock name='mock.query().filter().first().uuid' id='4402429520'>",
      "description": "Advance skills and abilities",
      "goal_type": "GoalType.PERSONAL",
      "priority": "GoalPriority.MEDIUM",
      "status": "GoalStatus.ACTIVE",
      "progress": 0.0,
      "parent_goal_id": null,
      "metadata": {},
      "created_at": "2025-05-25T01:26:24.636405",
      "updated_at": "2025-05-25T01:26:24.636406",
      "subgoals": []
    },
    {
      "goal_id": "dc3e924f-8d52-4a81-9c5a-4780dfa69938",
      "character_id": "<MagicMock name='mock.query().filter().first().uuid' id='4402429520'>",
      "description": "Build reputation in the world",
      "goal_type": "GoalType.NARRATIVE",
      "priority": "GoalPriority.LOW",
      "status": "GoalStatus.ACTIVE",
      "progress": 0.0,
      "parent_goal_id": null,
      "metadata": {
        "long_term": true
      },
      "created_at": "2025-05-25T01:26:24.636754",
      "updated_at": "2025-05-25T01:26:24.636754",
      "subgoals": []
    }
  ]
}